README.md
setup.cfg
setup.py
distributions_SKG/Binomialdistribution.py
distributions_SKG/Gaussiandistribution.py
distributions_SKG/Generaldistribution.py
distributions_SKG/__init__.py
distributions_SKG.egg-info/PKG-INFO
distributions_SKG.egg-info/SOURCES.txt
distributions_SKG.egg-info/dependency_links.txt
distributions_SKG.egg-info/not-zip-safe
distributions_SKG.egg-info/top_level.txt